exportmd/__init__.py
exportmd/core/chart_handler.py
exportmd/core/converter.py
exportmd/exporters/__init__.py
exportmd/exporters/docx.py
exportmd/exporters/html.py
exportmd/exporters/pdf.py
exportmd/exporters/pptx.py
exportmd/static/styles.py
exportmd-0.1.2.dist-info/licenses/LICENSE
exportmd-0.1.2.dist-info/METADATA
exportmd-0.1.2.dist-info/WHEEL
exportmd-0.1.2.dist-info/top_level.txt
exportmd-0.1.2.dist-info/RECORD
